Workbook

Sheet Assumptions
A1: DecisionMesh — Financial Model Assumptions
A2: 🔵 Blue text = input you can change | ⚫ Black text = calculated | Yellow bg = key assumption
A4: 1. PRICING MODEL
A5: Tier | B5: Monthly Price ($) | C5: Credits / Month | D5: Notes
A6: Hobby (free) | B6: 0 | C6: 500 | D6: Capped at 200 users max — free tier
A7: Builder | B7: 19 | C7: 2000 | D7: ← Primary revenue driver; fits expense approval
A8: Pro | B8: 49 | C8: 6000 | D8: 5 team seats; multi-project
A9: Team | B9: 149 | C9: 20000 | D9: 10 seats; SSO; priority SLA
A11: 2. LLM COST MODEL (per credit consumed)
A12: Model Tier | B12: Credits per Intent | C12: LLM Cost per Intent | D12: Effective Cost per Credit
A13: Economy (GPT-4o-mini / Haiku) | B13: 1 | C13: 0.004 | D13: =C13/B13 -> 0.004
A14: Standard (GPT-4o / Sonnet) | B14: 5 | C14: 0.018 | D14: =C14/B14 -> 0.0036
A15: Premium (Claude Opus / GPT-4) | B15: 25 | C15: 0.11 | D15: =C15/B15 -> 0.0044
A17: Blended LLM cost per credit (conservative — mostly Economy) | B17: 0.004
A18: Revenue per credit ($0.008 = $8 per 1,000 cr) | B18: 0.008
A20: 3. GROWTH & CONVERSION ASSUMPTIONS
A21: Parameter | B21: Rate / Value | C21: Conservative | D21: Notes
A22: Monthly new signups (Month 1) | B22: 20 | C22: 12 | D22: Organic: friends, social media, HN
A23: Monthly new signups (Month 12) | B23: 220 | C23: 140 | D23: SEO + referrals kicking in
A24: Monthly new signups (Month 24) | B24: 560 | C24: 350 | D24: Consistent content + referral flywheel
A25: Free → Builder conversion rate | B25: 0.05 | C25: 0.03 | D25: Industry avg for dev tools: 3–8%
A26: Builder → Pro upgrade (annual) | B26: 0.12 | C26: 0.08 | D26: Users who grow into multi-project
A27: Pro → Team upgrade (annual) | B27: 0.08 | C27: 0.05 | D27: Teams adding seats
A28: Hobby monthly churn | B28: 0.2 | C28: 0.25 | D28: High — free users disengage quickly
A29: Builder monthly churn | B29: 0.05 | C29: 0.07 | D29: Good B2B SaaS benchmark: 2–5%
A30: Pro monthly churn | B30: 0.03 | C30: 0.05 | D30: Higher stickiness at Pro level
A31: Team monthly churn | B31: 0.02 | C31: 0.03 | D31: Multi-seat — highest retention
A32: Hobby user hard cap (total) | B32: 200 | C32: 150 | D32: Safety cap — prevents free-tier abuse
A33: Credit pack attach rate (mo) | B33: 0.05 | C33: 0.03 | D33: % of paid users buying extra credits
... A35: Registration gift cost ($) | B35: 2 | C35: 2 | D35: 500 credits × $0.004 LLM cost
A37: 4. INFRASTRUCTURE COST SCHEDULE (Fly.io stack)
A38: Period | B38: $/month | C38: Month range | D38: Components
A39: Month 1–3 | B39: 35 | D39: Fly.io API ($15) + Postgres ($5) + Keycloak ($5) + Redis free + Cloudflare Pages free
A40: Month 4–6 | B40: 50 | D40: Upgraded Fly.io + Redis paid tier
A41: Month 7–12 | B41: 70 | D41: Redundant instances, larger Postgres, backups
A42: Month 13–18 | B42: 100 | D42: Multi-region, CDN, monitoring stack
A43: Month 19–24 | B43: 130 | D43: Scaled infra for 500+ paid users
A45: 5. STRIPE FEES
A46: Stripe % fee per transaction | B46: 0.029
A47: Stripe flat fee per transaction ($) | B47: 0.3

Sheet Monthly P&L
A1: DecisionMesh — 24-Month Monthly P&L
A3: Metric | B3: M1 | C3: M2 | D3: M3 | E3: M4 | F3: M5 | G3: M6 | H3: M7 | I3: M8 | J3: M9 | K3: M10 | L3: M11 | M3: M12 | N3: M13 | O3: M14 | P3: M15 | Q3: M16 | R3: M17 | S3: M18 | T3: M19 | U3: M20 | V3: M21 | W3: M22 | X3: M23 | Y3: M24
A5: New signups (organic) | B5: 20 | C5: 30 | D5: 45 | E5: 60 | F5: 80 | G5: 100 | H5: 120 | I5: 140 | J5: 160 | K5: 180 | L5: 200 | M5: 220 | N5: 240 | O5: 260 | P5: 280 | Q5: 300 | R5: 330 | S5: 360 | T5: 390 | U5: 420 | V5: 450 | W5: 480 | X5: 520 | Y5: 560
A6: SUBSCRIBERS (end of month)
A7: Hobby subscribers (free) | B7: =MIN(Assumptions!B32, ROUND(B5*Assumptions!B25*0.5, 0)) -> 1 | C7: =MIN(Assumptions!B32, ROUND(B7*(1-Assumptions!B28)+C5*Assumptions!B25*0.5, 0)) -> 2 | D7: =MIN(Assumptions!B32, ROUND(C7*(1-Assumptions!B28)+D5*Assumptions!B25*0.5, 0)) -> 3 | E7: =MIN(Assumptions!B32, ROUND(D7*(1-Assumptions!B28)+E5*Assumptions!B25*0.5, 0)) -> 4 | F7: =MIN(Assumptions!B32, ROUND(E7*(1-Assumptions!B28)+F5*Assumptions!B25*0.5, 0)) -> 5 | G7: =MIN(Assumptions!B32, ROUND(F7*(1-Assumptions!B28)+G5*Assumptions!B25*0.5, 0)) -> 7 | H7: =MIN(Assumptions!B32, ROUND(G7*(1-Assumptions!B28)+H5*Assumptions!B25*0.5, 0)) -> 9 | I7: =MIN(Assumptions!B32, ROUND(H7*(1-Assumptions!B28)+I5*Assumptions!B25*0.5, 0)) -> 11 | J7: =MIN(Assumptions!B32, ROUND(I7*(1-Assumptions!B28)+J5*Assumptions!B25*0.5, 0)) -> 13 | K7: =MIN(Assumptions!B32, ROUND(J7*(1-Assumptions!B28)+K5*Assumptions!B25*0.5, 0)) -> 15 | L7: =MIN(Assumptions!B32, ROUND(K7*(1-Assumptions!B28)+L5*Assumptions!B25*0.5, 0)) -> 17 | M7: =MIN(Assumptions!B32, ROUND(L7*(1-Assumptions!B28)+M5*Assumptions!B25*0.5, 0)) -> 19 | N7: =MIN(Assumptions!B32, ROUND(M7*(1-Assumptions!B28)+N5*Assumptions!B25*0.5, 0)) -> 21 | O7: =MIN(Assumptions!B32, ROUND(N7*(1-Assumptions!B28)+O5*Assumptions!B25*0.5, 0)) -> 23 | P7: =MIN(Assumptions!B32, ROUND(O7*(1-Assumptions!B28)+P5*Assumptions!B25*0.5, 0)) -> 25 | Q7: =MIN(Assumptions!B32, ROUND(P7*(1-Assumptions!B28)+Q5*Assumptions!B25*0.5, 0)) -> 28 | R7: =MIN(Assumptions!B32, ROUND(Q7*(1-Assumptions!B28)+R5*Assumptions!B25*0.5, 0)) -> 31 | S7: =MIN(Assumptions!B32, ROUND(R7*(1-Assumptions!B28)+S5*Assumptions!B25*0.5, 0)) -> 34 | T7: =MIN(Assumptions!B32, ROUND(S7*(1-Assumptions!B28)+T5*Assumptions!B25*0.5, 0)) -> 37 | U7: =MIN(Assumptions!B32, ROUND(T7*(1-Assumptions!B28)+U5*Assumptions!B25*0.5, 0)) -> 40 | V7: =MIN(Assumptions!B32, ROUND(U7*(1-Assumptions!B28)+V5*Assumptions!B25*0.5, 0)) -> 43 | W7: =MIN(Assumptions!B32, ROUND(V7*(1-Assumptions!B28)+W5*Assumptions!B25*0.5, 0)) -> 46 | X7: =MIN(Assumptions!B32, ROUND(W7*(1-Assumptions!B28)+X5*Assumptions!B25*0.5, 0)) -> 50 | Y7: =MIN(Assumptions!B32, ROUND(X7*(1-Assumptions!B28)+Y5*Assumptions!B25*0.5, 0)) -> 54
A8: Builder subscribers ($19) | B8: =ROUND(B5*Assumptions!B25, 0) -> 1 | C8: =MAX(0, ROUND(B8*(1-Assumptions!B29)+C5*Assumptions!B25, 0)) -> 2 | D8: =MAX(0, ROUND(C8*(1-Assumptions!B29)+D5*Assumptions!B25, 0)) -> 4 | E8: =MAX(0, ROUND(D8*(1-Assumptions!B29)+E5*Assumptions!B25, 0)) -> 7 | F8: =MAX(0, ROUND(E8*(1-Assumptions!B29)+F5*Assumptions!B25, 0)) -> 11 | G8: =MAX(0, ROUND(F8*(1-Assumptions!B29)+G5*Assumptions!B25, 0)) -> 15 | H8: =MAX(0, ROUND(G8*(1-Assumptions!B29)+H5*Assumptions!B25, 0)) -> 20 | I8: =MAX(0, ROUND(H8*(1-Assumptions!B29)+I5*Assumptions!B25, 0)) -> 26 | J8: =MAX(0, ROUND(I8*(1-Assumptions!B29)+J5*Assumptions!B25, 0)) -> 33 | K8: =MAX(0, ROUND(J8*(1-Assumptions!B29)+K5*Assumptions!B25, 0)) -> 40 | L8: =MAX(0, ROUND(K8*(1-Assumptions!B29)+L5*Assumptions!B25, 0)) -> 48 | M8: =MAX(0, ROUND(L8*(1-Assumptions!B29)+M5*Assumptions!B25, 0)) -> 57 | N8: =MAX(0, ROUND(M8*(1-Assumptions!B29)+N5*Assumptions!B25, 0)) -> 66 | O8: =MAX(0, ROUND(N8*(1-Assumptions!B29)+O5*Assumptions!B25, 0)) -> 76 | P8: =MAX(0, ROUND(O8*(1-Assumptions!B29)+P5*Assumptions!B25, 0)) -> 86 | Q8: =MAX(0, ROUND(P8*(1-Assumptions!B29)+Q5*Assumptions!B25, 0)) -> 97 | R8: =MAX(0, ROUND(Q8*(1-Assumptions!B29)+R5*Assumptions!B25, 0)) -> 109 | S8: =MAX(0, ROUND(R8*(1-Assumptions!B29)+S5*Assumptions!B25, 0)) -> 122 | T8: =MAX(0, ROUND(S8*(1-Assumptions!B29)+T5*Assumptions!B25, 0)) -> 135 | U8: =MAX(0, ROUND(T8*(1-Assumptions!B29)+U5*Assumptions!B25, 0)) -> 149 | V8: =MAX(0, ROUND(U8*(1-Assumptions!B29)+V5*Assumptions!B25, 0)) -> 164 | W8: =MAX(0, ROUND(V8*(1-Assumptions!B29)+W5*Assumptions!B25, 0)) -> 180 | X8: =MAX(0, ROUND(W8*(1-Assumptions!B29)+X5*Assumptions!B25, 0)) -> 197 | Y8: =MAX(0, ROUND(X8*(1-Assumptions!B29)+Y5*Assumptions!B25, 0)) -> 215
A9: Pro subscribers ($49) | B9: =0 -> 0 | C9: =MAX(0, ROUND(B9*(1-Assumptions!B30)+ROUND(B8*Assumptions!B26/12, 0)-ROUND(B9*Assumptions!B27/12, 0), 0)) -> 0 | D9: =MAX(0, ROUND(C9*(1-Assumptions!B30)+ROUND(C8*Assumptions!B26/12, 0)-ROUND(C9*Assumptions!B27/12, 0), 0)) -> 0 | E9: =MAX(0, ROUND(D9*(1-Assumptions!B30)+ROUND(D8*Assumptions!B26/12, 0)-ROUND(D9*Assumptions!B27/12, 0), 0)) -> 0 | F9: =MAX(0, ROUND(E9*(1-Assumptions!B30)+ROUND(E8*Assumptions!B26/12, 0)-ROUND(E9*Assumptions!B27/12, 0), 0)) -> 0 | G9: =MAX(0, ROUND(F9*(1-Assumptions!B30)+ROUND(F8*Assumptions!B26/12, 0)-ROUND(F9*Assumptions!B27/12, 0), 0)) -> 0 | H9: =MAX(0, ROUND(G9*(1-Assumptions!B30)+ROUND(G8*Assumptions!B26/12, 0)-ROUND(G9*Assumptions!B27/12, 0), 0)) -> 0 | I9: =MAX(0, ROUND(H9*(1-Assumptions!B30)+ROUND(H8*Assumptions!B26/12, 0)-ROUND(H9*Assumptions!B27/12, 0), 0)) -> 0 | J9: =MAX(0, ROUND(I9*(1-Assumptions!B30)+ROUND(I8*Assumptions!B26/12, 0)-ROUND(I9*Assumptions!B27/12, 0), 0)) -> 0 | K9: =MAX(0, ROUND(J9*(1-Assumptions!B30)+ROUND(J8*Assumptions!B26/12, 0)-ROUND(J9*Assumptions!B27/12, 0), 0)) -> 0 | L9: =MAX(0, ROUND(K9*(1-Assumptions!B30)+ROUND(K8*Assumptions!B26/12, 0)-ROUND(K9*Assumptions!B27/12, 0), 0)) -> 0 | M9: =MAX(0, ROUND(L9*(1-Assumptions!B30)+ROUND(L8*Assumptions!B26/12, 0)-ROUND(L9*Assumptions!B27/12, 0), 0)) -> 0 | N9: =MAX(0, ROUND(M9*(1-Assumptions!B30)+ROUND(M8*Assumptions!B26/12, 0)-ROUND(M9*Assumptions!B27/12, 0), 0)) -> 1 | O9: =MAX(0, ROUND(N9*(1-Assumptions!B30)+ROUND(N8*Assumptions!B26/12, 0)-ROUND(N9*Assumptions!B27/12, 0), 0)) -> 2 | P9: =MAX(0, ROUND(O9*(1-Assumptions!B30)+ROUND(O8*Assumptions!B26/12, 0)-ROUND(O9*Assumptions!B27/12, 0), 0)) -> 3 | Q9: =MAX(0, ROUND(P9*(1-Assumptions!B30)+ROUND(P8*Assumptions!B26/12, 0)-ROUND(P9*Assumptions!B27/12, 0), 0)) -> 4 | R9: =MAX(0, ROUND(Q9*(1-Assumptions!B30)+ROUND(Q8*Assumptions!B26/12, 0)-ROUND(Q9*Assumptions!B27/12, 0), 0)) -> 5 | S9: =MAX(0, ROUND(R9*(1-Assumptions!B30)+ROUND(R8*Assumptions!B26/12, 0)-ROUND(R9*Assumptions!B27/12, 0), 0)) -> 6 | T9: =MAX(0, ROUND(S9*(1-Assumptions!B30)+ROUND(S8*Assumptions!B26/12, 0)-ROUND(S9*Assumptions!B27/12, 0), 0)) -> 7 | U9: =MAX(0, ROUND(T9*(1-Assumptions!B30)+ROUND(T8*Assumptions!B26/12, 0)-ROUND(T9*Assumptions!B27/12, 0), 0)) -> 8 | V9: =MAX(0, ROUND(U9*(1-Assumptions!B30)+ROUND(U8*Assumptions!B26/12, 0)-ROUND(U9*Assumptions!B27/12, 0), 0)) -> 9 | W9: =MAX(0, ROUND(V9*(1-Assumptions!B30)+ROUND(V8*Assumptions!B26/12, 0)-ROUND(V9*Assumptions!B27/12, 0), 0)) -> 11 | X9: =MAX(0, ROUND(W9*(1-Assumptions!B30)+ROUND(W8*Assumptions!B26/12, 0)-ROUND(W9*Assumptions!B27/12, 0), 0)) -> 13 | Y9: =MAX(0, ROUND(X9*(1-Assumptions!B30)+ROUND(X8*Assumptions!B26/12, 0)-ROUND(X9*Assumptions!B27/12, 0), 0)) -> 15
A10: Team subscribers ($149) | B10: =0 -> 0 | C10: =MAX(0, ROUND(B10*(1-Assumptions!B31)+ROUND(B9*Assumptions!B27/12, 0), 0)) -> 0 | D10: =MAX(0, ROUND(C10*(1-Assumptions!B31)+ROUND(C9*Assumptions!B27/12, 0), 0)) -> 0 | E10: =MAX(0, ROUND(D10*(1-Assumptions!B31)+ROUND(D9*Assumptions!B27/12, 0), 0)) -> 0 | F10: =MAX(0, ROUND(E10*(1-Assumptions!B31)+ROUND(E9*Assumptions!B27/12, 0), 0)) -> 0 | G10: =MAX(0, ROUND(F10*(1-Assumptions!B31)+ROUND(F9*Assumptions!B27/12, 0), 0)) -> 0 | H10: =MAX(0, ROUND(G10*(1-Assumptions!B31)+ROUND(G9*Assumptions!B27/12, 0), 0)) -> 0 | I10: =MAX(0, ROUND(H10*(1-Assumptions!B31)+ROUND(H9*Assumptions!B27/12, 0), 0)) -> 0 | J10: =MAX(0, ROUND(I10*(1-Assumptions!B31)+ROUND(I9*Assumptions!B27/12, 0), 0)) -> 0 | K10: =MAX(0, ROUND(J10*(1-Assumptions!B31)+ROUND(J9*Assumptions!B27/12, 0), 0)) -> 0 | L10: =MAX(0, ROUND(K10*(1-Assumptions!B31)+ROUND(K9*Assumptions!B27/12, 0), 0)) -> 0 | M10: =MAX(0, ROUND(L10*(1-Assumptions!B31)+ROUND(L9*Assumptions!B27/12, 0), 0)) -> 0 | N10: =MAX(0, ROUND(M10*(1-Assumptions!B31)+ROUND(M9*Assumptions!B27/12, 0), 0)) -> 0 | O10: =MAX(0, ROUND(N10*(1-Assumptions!B31)+ROUND(N9*Assumptions!B27/12, 0), 0)) -> 0 | P10: =MAX(0, ROUND(O10*(1-Assumptions!B31)+ROUND(O9*Assumptions!B27/12, 0), 0)) -> 0 | Q10: =MAX(0, ROUND(P10*(1-Assumptions!B31)+ROUND(P9*Assumptions!B27/12, 0), 0)) -> 0 | R10: =MAX(0, ROUND(Q10*(1-Assumptions!B31)+ROUND(Q9*Assumptions!B27/12, 0), 0)) -> 0 | S10: =MAX(0, ROUND(R10*(1-Assumptions!B31)+ROUND(R9*Assumptions!B27/12, 0), 0)) -> 0 | T10: =MAX(0, ROUND(S10*(1-Assumptions!B31)+ROUND(S9*Assumptions!B27/12, 0), 0)) -> 0 | U10: =MAX(0, ROUND(T10*(1-Assumptions!B31)+ROUND(T9*Assumptions!B27/12, 0), 0)) -> 0 | V10: =MAX(0, ROUND(U10*(1-Assumptions!B31)+ROUND(U9*Assumptions!B27/12, 0), 0)) -> 0 | W10: =MAX(0, ROUND(V10*(1-Assumptions!B31)+ROUND(V9*Assumptions!B27/12, 0), 0)) -> 0 | X10: =MAX(0, ROUND(W10*(1-Assumptions!B31)+ROUND(W9*Assumptions!B27/12, 0), 0)) -> 0 | Y10: =MAX(0, ROUND(X10*(1-Assumptions!B31)+ROUND(X9*Assumptions!B27/12, 0), 0)) -> 0
A11: Total paid subscribers | B11: =B8+B9+B10 -> 1 | C11: =C8+C9+C10 -> 2 | D11: =D8+D9+D10 -> 4 | E11: =E8+E9+E10 -> 7 | F11: =F8+F9+F10 -> 11 | G11: =G8+G9+G10 -> 15 | H11: =H8+H9+H10 -> 20 | I11: =I8+I9+I10 -> 26 | ... Y11: =Y8+Y9+Y10 -> 230
A13: REVENUE ($)
A14: Builder revenue | B14: =B8*Assumptions!B7 -> 19 | C14: =C8*Assumptions!B7 -> 38 | D14: =D8*Assumptions!B7 -> 76 | E14: =E8*Assumptions!B7 -> 133 | F14: =F8*Assumptions!B7 -> 209 | G14: =G8*Assumptions!B7 -> 285 | H14: =H8*Assumptions!B7 -> 380 | I14: =I8*Assumptions!B7 -> 494 | J14: =J8*Assumptions!B7 -> 627 | K14: =K8*Assumptions!B7 -> 760 | L14: =L8*Assumptions!B7 -> 912 | M14: =M8*Assumptions!B7 -> 1083 | N14: =N8*Assumptions!B7 -> 1254 | O14: =O8*Assumptions!B7 -> 1444 | P14: =P8*Assumptions!B7 -> 1634 | Q14: =Q8*Assumptions!B7 -> 1843 | R14: =R8*Assumptions!B7 -> 2071 | S14: =S8*Assumptions!B7 -> 2318 | T14: =T8*Assumptions!B7 -> 2565 | U14: =U8*Assumptions!B7 -> 2831 | V14: =V8*Assumptions!B7 -> 3116 | W14: =W8*Assumptions!B7 -> 3420 | X14: =X8*Assumptions!B7 -> 3743 | Y14: =Y8*Assumptions!B7 -> 4085
A15: Pro revenue | B15: =B9*Assumptions!B8 -> 0 | C15: =C9*Assumptions!B8 -> 0 | D15: =D9*Assumptions!B8 -> 0 | E15: =E9*Assumptions!B8 -> 0 | F15: =F9*Assumptions!B8 -> 0 | G15: =G9*Assumptions!B8 -> 0 | H15: =H9*Assumptions!B8 -> 0 | I15: =I9*Assumptions!B8 -> 0 | J15: =J9*Assumptions!B8 -> 0 | K15: =K9*Assumptions!B8 -> 0 | L15: =L9*Assumptions!B8 -> 0 | M15: =M9*Assumptions!B8 -> 0 | N15: =N9*Assumptions!B8 -> 49 | O15: =O9*Assumptions!B8 -> 98 | P15: =P9*Assumptions!B8 -> 147 | Q15: =Q9*Assumptions!B8 -> 196 | R15: =R9*Assumptions!B8 -> 245 | S15: =S9*Assumptions!B8 -> 294 | T15: =T9*Assumptions!B8 -> 343 | U15: =U9*Assumptions!B8 -> 392 | V15: =V9*Assumptions!B8 -> 441 | W15: =W9*Assumptions!B8 -> 539 | X15: =X9*Assumptions!B8 -> 637 | Y15: =Y9*Assumptions!B8 -> 735
A16: Team revenue | B16: =B10*Assumptions!B9 -> 0 | C16: =C10*Assumptions!B9 -> 0 | D16: =D10*Assumptions!B9 -> 0 | E16: =E10*Assumptions!B9 -> 0 | F16: =F10*Assumptions!B9 -> 0 | G16: =G10*Assumptions!B9 -> 0 | H16: =H10*Assumptions!B9 -> 0 | I16: =I10*Assumptions!B9 -> 0 | J16: =J10*Assumptions!B9 -> 0 | K16: =K10*Assumptions!B9 -> 0 | L16: =L10*Assumptions!B9 -> 0 | M16: =M10*Assumptions!B9 -> 0 | N16: =N10*Assumptions!B9 -> 0 | O16: =O10*Assumptions!B9 -> 0 | P16: =P10*Assumptions!B9 -> 0 | Q16: =Q10*Assumptions!B9 -> 0 | R16: =R10*Assumptions!B9 -> 0 | S16: =S10*Assumptions!B9 -> 0 | T16: =T10*Assumptions!B9 -> 0 | U16: =U10*Assumptions!B9 -> 0 | V16: =V10*Assumptions!B9 -> 0 | W16: =W10*Assumptions!B9 -> 0 | X16: =X10*Assumptions!B9 -> 0 | Y16: =Y10*Assumptions!B9 -> 0
A17: Credit pack revenue | B17: =B11*Assumptions!B33*Assumptions!B34 -> 1.25 | C17: =C11*Assumptions!B33*Assumptions!B34 -> 2.5 | D17: =D11*Assumptions!B33*Assumptions!B34 -> 5 | E17: =E11*Assumptions!B33*Assumptions!B34 -> 8.75 | F17: =F11*Assumptions!B33*Assumptions!B34 -> 13.75 | G17: =G11*Assumptions!B33*Assumptions!B34 -> 18.75 | H17: =H11*Assumptions!B33*Assumptions!B34 -> 25 | I17: =I11*Assumptions!B33*Assumptions!B34 -> 32.5 | J17: =J11*Assumptions!B33*Assumptions!B34 -> 41.25 | K17: =K11*Assumptions!B33*Assumptions!B34 -> 50 | L17: =L11*Assumptions!B33*Assumptions!B34 -> 60 | M17: =M11*Assumptions!B33*Assumptions!B34 -> 71.25 | N17: =N11*Assumptions!B33*Assumptions!B34 -> 83.75 | O17: =O11*Assumptions!B33*Assumptions!B34 -> 97.5 | P17: =P11*Assumptions!B33*Assumptions!B34 -> 111.25 | Q17: =Q11*Assumptions!B33*Assumptions!B34 -> 126.25 | R17: =R11*Assumptions!B33*Assumptions!B34 -> 142.5 | S17: =S11*Assumptions!B33*Assumptions!B34 -> 160 | T17: =T11*Assumptions!B33*Assumptions!B34 -> 177.5 | U17: =U11*Assumptions!B33*Assumptions!B34 -> 196.25 | V17: =V11*Assumptions!B33*Assumptions!B34 -> 216.25 | W17: =W11*Assumptions!B33*Assumptions!B34 -> 238.75 | X17: =X11*Assumptions!B33*Assumptions!B34 -> 262.5 | Y17: =Y11*Assumptions!B33*Assumptions!B34 -> 287.5
A18: TOTAL REVENUE | B18: =B14+B15+B16+B17 -> 20.25 | C18: =C14+C15+C16+C17 -> 40.5 | D18: =D14+D15+D16+D17 -> 81 | E18: =E14+E15+E16+E17 -> 141.75 | F18: =F14+F15+F16+F17 -> 222.75 | G18: =G14+G15+G16+G17 -> 303.75 | H18: =H14+H15+H16+H17 -> 405 | I18: =I14+I15+I16+I17 -> 526.5 | ... Y18: =Y14+Y15+Y16+Y17 -> 5107.5
A20: COSTS ($)
A21: LLM — Hobby users | B21: =B7*Assumptions!C6*Assumptions!B17 -> 2 | C21: =C7*Assumptions!C6*Assumptions!B17 -> 4 | D21: =D7*Assumptions!C6*Assumptions!B17 -> 6 | E21: =E7*Assumptions!C6*Assumptions!B17 -> 8 | F21: =F7*Assumptions!C6*Assumptions!B17 -> 10 | G21: =G7*Assumptions!C6*Assumptions!B17 -> 14 | H21: =H7*Assumptions!C6*Assumptions!B17 -> 18 | I21: =I7*Assumptions!C6*Assumptions!B17 -> 22 | J21: =J7*Assumptions!C6*Assumptions!B17 -> 26 | K21: =K7*Assumptions!C6*Assumptions!B17 -> 30 | L21: =L7*Assumptions!C6*Assumptions!B17 -> 34 | M21: =M7*Assumptions!C6*Assumptions!B17 -> 38 | N21: =N7*Assumptions!C6*Assumptions!B17 -> 42 | O21: =O7*Assumptions!C6*Assumptions!B17 -> 46 | P21: =P7*Assumptions!C6*Assumptions!B17 -> 50 | Q21: =Q7*Assumptions!C6*Assumptions!B17 -> 56 | R21: =R7*Assumptions!C6*Assumptions!B17 -> 62 | S21: =S7*Assumptions!C6*Assumptions!B17 -> 68 | T21: =T7*Assumptions!C6*Assumptions!B17 -> 74 | U21: =U7*Assumptions!C6*Assumptions!B17 -> 80 | V21: =V7*Assumptions!C6*Assumptions!B17 -> 86 | W21: =W7*Assumptions!C6*Assumptions!B17 -> 92 | X21: =X7*Assumptions!C6*Assumptions!B17 -> 100 | Y21: =Y7*Assumptions!C6*Assumptions!B17 -> 108
A22: LLM — Builder users | B22: =B8*Assumptions!C7*Assumptions!B17 -> 8 | C22: =C8*Assumptions!C7*Assumptions!B17 -> 16 | D22: =D8*Assumptions!C7*Assumptions!B17 -> 32 | E22: =E8*Assumptions!C7*Assumptions!B17 -> 56 | F22: =F8*Assumptions!C7*Assumptions!B17 -> 88 | G22: =G8*Assumptions!C7*Assumptions!B17 -> 120 | H22: =H8*Assumptions!C7*Assumptions!B17 -> 160 | I22: =I8*Assumptions!C7*Assumptions!B17 -> 208 | J22: =J8*Assumptions!C7*Assumptions!B17 -> 264 | K22: =K8*Assumptions!C7*Assumptions!B17 -> 320 | L22: =L8*Assumptions!C7*Assumptions!B17 -> 384 | M22: =M8*Assumptions!C7*Assumptions!B17 -> 456 | N22: =N8*Assumptions!C7*Assumptions!B17 -> 528 | O22: =O8*Assumptions!C7*Assumptions!B17 -> 608 | P22: =P8*Assumptions!C7*Assumptions!B17 -> 688 | Q22: =Q8*Assumptions!C7*Assumptions!B17 -> 776 | R22: =R8*Assumptions!C7*Assumptions!B17 -> 872 | S22: =S8*Assumptions!C7*Assumptions!B17 -> 976 | T22: =T8*Assumptions!C7*Assumptions!B17 -> 1080 | U22: =U8*Assumptions!C7*Assumptions!B17 -> 1192 | V22: =V8*Assumptions!C7*Assumptions!B17 -> 1312 | W22: =W8*Assumptions!C7*Assumptions!B17 -> 1440 | X22: =X8*Assumptions!C7*Assumptions!B17 -> 1576 | Y22: =Y8*Assumptions!C7*Assumptions!B17 -> 1720
A23: LLM — Pro users | B23: =B9*Assumptions!C8*Assumptions!B17 -> 0 | C23: =C9*Assumptions!C8*Assumptions!B17 -> 0 | D23: =D9*Assumptions!C8*Assumptions!B17 -> 0 | E23: =E9*Assumptions!C8*Assumptions!B17 -> 0 | F23: =F9*Assumptions!C8*Assumptions!B17 -> 0 | G23: =G9*Assumptions!C8*Assumptions!B17 -> 0 | H23: =H9*Assumptions!C8*Assumptions!B17 -> 0 | I23: =I9*Assumptions!C8*Assumptions!B17 -> 0 | J23: =J9*Assumptions!C8*Assumptions!B17 -> 0 | K23: =K9*Assumptions!C8*Assumptions!B17 -> 0 | L23: =L9*Assumptions!C8*Assumptions!B17 -> 0 | M23: =M9*Assumptions!C8*Assumptions!B17 -> 0 | N23: =N9*Assumptions!C8*Assumptions!B17 -> 24 | O23: =O9*Assumptions!C8*Assumptions!B17 -> 48 | P23: =P9*Assumptions!C8*Assumptions!B17 -> 72 | Q23: =Q9*Assumptions!C8*Assumptions!B17 -> 96 | R23: =R9*Assumptions!C8*Assumptions!B17 -> 120 | S23: =S9*Assumptions!C8*Assumptions!B17 -> 144 | T23: =T9*Assumptions!C8*Assumptions!B17 -> 168 | U23: =U9*Assumptions!C8*Assumptions!B17 -> 192 | V23: =V9*Assumptions!C8*Assumptions!B17 -> 216 | W23: =W9*Assumptions!C8*Assumptions!B17 -> 264 | X23: =X9*Assumptions!C8*Assumptions!B17 -> 312 | Y23: =Y9*Assumptions!C8*Assumptions!B17 -> 360
A24: LLM — Team users | B24: =B10*Assumptions!C9*Assumptions!B17 -> 0 | C24: =C10*Assumptions!C9*Assumptions!B17 -> 0 | D24: =D10*Assumptions!C9*Assumptions!B17 -> 0 | E24: =E10*Assumptions!C9*Assumptions!B17 -> 0 | F24: =F10*Assumptions!C9*Assumptions!B17 -> 0 | G24: =G10*Assumptions!C9*Assumptions!B17 -> 0 | H24: =H10*Assumptions!C9*Assumptions!B17 -> 0 | I24: =I10*Assumptions!C9*Assumptions!B17 -> 0 | J24: =J10*Assumptions!C9*Assumptions!B17 -> 0 | K24: =K10*Assumptions!C9*Assumptions!B17 -> 0 | L24: =L10*Assumptions!C9*Assumptions!B17 -> 0 | M24: =M10*Assumptions!C9*Assumptions!B17 -> 0 | N24: =N10*Assumptions!C9*Assumptions!B17 -> 0 | O24: =O10*Assumptions!C9*Assumptions!B17 -> 0 | P24: =P10*Assumptions!C9*Assumptions!B17 -> 0 | Q24: =Q10*Assumptions!C9*Assumptions!B17 -> 0 | R24: =R10*Assumptions!C9*Assumptions!B17 -> 0 | S24: =S10*Assumptions!C9*Assumptions!B17 -> 0 | T24: =T10*Assumptions!C9*Assumptions!B17 -> 0 | U24: =U10*Assumptions!C9*Assumptions!B17 -> 0 | V24: =V10*Assumptions!C9*Assumptions!B17 -> 0 | W24: =W10*Assumptions!C9*Assumptions!B17 -> 0 | X24: =X10*Assumptions!C9*Assumptions!B17 -> 0 | Y24: =Y10*Assumptions!C9*Assumptions!B17 -> 0
A25: LLM — Registration gifts | B25: =B5*Assumptions!B35 -> 40 | C25: =C5*Assumptions!B35 -> 60 | D25: =D5*Assumptions!B35 -> 90 | E25: =E5*Assumptions!B35 -> 120 | F25: =F5*Assumptions!B35 -> 160 | G25: =G5*Assumptions!B35 -> 200 | H25: =H5*Assumptions!B35 -> 240 | I25: =I5*Assumptions!B35 -> 280 | J25: =J5*Assumptions!B35 -> 320 | K25: =K5*Assumptions!B35 -> 360 | L25: =L5*Assumptions!B35 -> 400 | M25: =M5*Assumptions!B35 -> 440 | N25: =N5*Assumptions!B35 -> 480 | O25: =O5*Assumptions!B35 -> 520 | P25: =P5*Assumptions!B35 -> 560 | Q25: =Q5*Assumptions!B35 -> 600 | R25: =R5*Assumptions!B35 -> 660 | S25: =S5*Assumptions!B35 -> 720 | T25: =T5*Assumptions!B35 -> 780 | U25: =U5*Assumptions!B35 -> 840 | V25: =V5*Assumptions!B35 -> 900 | W25: =W5*Assumptions!B35 -> 960 | X25: =X5*Assumptions!B35 -> 1040 | Y25: =Y5*Assumptions!B35 -> 1120
A26: LLM — Credit pack credits | B26: =B17/Assumptions!B17*Assumptions!B17*0.5 -> 0.625 | C26: =C17/Assumptions!B17*Assumptions!B17*0.5 -> 1.25 | D26: =D17/Assumptions!B17*Assumptions!B17*0.5 -> 2.5 | E26: =E17/Assumptions!B17*Assumptions!B17*0.5 -> 4.375 | F26: =F17/Assumptions!B17*Assumptions!B17*0.5 -> 6.875 | G26: =G17/Assumptions!B17*Assumptions!B17*0.5 -> 9.375 | H26: =H17/Assumptions!B17*Assumptions!B17*0.5 -> 12.5 | I26: =I17/Assumptions!B17*Assumptions!B17*0.5 -> 16.25 | J26: =J17/Assumptions!B17*Assumptions!B17*0.5 -> 20.625 | K26: =K17/Assumptions!B17*Assumptions!B17*0.5 -> 25 | L26: =L17/Assumptions!B17*Assumptions!B17*0.5 -> 30 | M26: =M17/Assumptions!B17*Assumptions!B17*0.5 -> 35.625 | N26: =N17/Assumptions!B17*Assumptions!B17*0.5 -> 41.875 | O26: =O17/Assumptions!B17*Assumptions!B17*0.5 -> 48.75 | P26: =P17/Assumptions!B17*Assumptions!B17*0.5 -> 55.625 | Q26: =Q17/Assumptions!B17*Assumptions!B17*0.5 -> 63.125 | R26: =R17/Assumptions!B17*Assumptions!B17*0.5 -> 71.25 | S26: =S17/Assumptions!B17*Assumptions!B17*0.5 -> 80 | T26: =T17/Assumptions!B17*Assumptions!B17*0.5 -> 88.75 | U26: =U17/Assumptions!B17*Assumptions!B17*0.5 -> 98.125 | V26: =V17/Assumptions!B17*Assumptions!B17*0.5 -> 108.125 | W26: =W17/Assumptions!B17*Assumptions!B17*0.5 -> 119.375 | X26: =X17/Assumptions!B17*Assumptions!B17*0.5 -> 131.25 | Y26: =Y17/Assumptions!B17*Assumptions!B17*0.5 -> 143.75
A27: Total LLM cost | B27: =SUM(B21:B26) -> 50.625 | C27: =SUM(C21:C26) -> 81.25 | D27: =SUM(D21:D26) -> 130.5 | E27: =SUM(E21:E26) -> 188.375 | F27: =SUM(F21:F26) -> 264.875 | G27: =SUM(G21:G26) -> 343.375 | H27: =SUM(H21:H26) -> 430.5 | I27: =SUM(I21:I26) -> 526.25 | ... Y27: =SUM(Y21:Y26) -> 3451.75
A28: Infrastructure (Fly.io stack) | B28: 35 | C28: 35 | D28: 35 | E28: 50 | F28: 50 | G28: 50 | H28: 70 | I28: 70 | J28: 70 | K28: 70 | L28: 70 | M28: 70 | N28: 100 | O28: 100 | P28: 100 | Q28: 100 | R28: 100 | S28: 100 | T28: 130 | U28: 130 | V28: 130 | W28: 130 | X28: 130 | Y28: 130
A29: Stripe transaction fees | B29: =B18*Assumptions!B46+B11*Assumptions!B47 -> 0.88725 | C29: =C18*Assumptions!B46+C11*Assumptions!B47 -> 1.7745 | D29: =D18*Assumptions!B46+D11*Assumptions!B47 -> 3.549 | E29: =E18*Assumptions!B46+E11*Assumptions!B47 -> 6.21075 | F29: =F18*Assumptions!B46+F11*Assumptions!B47 -> 9.75975 | G29: =G18*Assumptions!B46+G11*Assumptions!B47 -> 13.30875 | H29: =H18*Assumptions!B46+H11*Assumptions!B47 -> 17.745 | I29: =I18*Assumptions!B46+I11*Assumptions!B47 -> 23.0685 | J29: =J18*Assumptions!B46+J11*Assumptions!B47 -> 29.27925 | K29: =K18*Assumptions!B46+K11*Assumptions!B47 -> 35.49 | L29: =L18*Assumptions!B46+L11*Assumptions!B47 -> 42.588 | M29: =M18*Assumptions!B46+M11*Assumptions!B47 -> 50.57325 | N29: =N18*Assumptions!B46+N11*Assumptions!B47 -> 60.31575 | O29: =O18*Assumptions!B46+O11*Assumptions!B47 -> 70.9455 | P29: =P18*Assumptions!B46+P11*Assumptions!B47 -> 81.57525 | Q29: =Q18*Assumptions!B46+Q11*Assumptions!B47 -> 93.09225 | R29: =R18*Assumptions!B46+R11*Assumptions!B47 -> 105.4965 | S29: =S18*Assumptions!B46+S11*Assumptions!B47 -> 118.788 | T29: =T18*Assumptions!B46+T11*Assumptions!B47 -> 132.0795 | U29: =U18*Assumptions!B46+U11*Assumptions!B47 -> 146.25825 | V29: =V18*Assumptions!B46+V11*Assumptions!B47 -> 161.32425 | W29: =W18*Assumptions!B46+W11*Assumptions!B47 -> 179.03475 | X29: =X18*Assumptions!B46+X11*Assumptions!B47 -> 197.6325 | Y29: =Y18*Assumptions!B46+Y11*Assumptions!B47 -> 217.1175
A30: TOTAL COSTS | B30: =B27+B28+B29 -> 86.51225 | C30: =C27+C28+C29 -> 118.0245 | D30: =D27+D28+D29 -> 169.049 | E30: =E27+E28+E29 -> 244.58575 | F30: =F27+F28+F29 -> 324.63475 | G30: =G27+G28+G29 -> 406.68375 | H30: =H27+H28+H29 -> 518.245 | I30: =I27+I28+I29 -> 619.3185 | ... Y30: =Y27+Y28+Y29 -> 3798.8675
A32: PROFITABILITY ($)
A33: Gross profit (rev − LLM − Stripe) | B33: =B18-B27-B29 -> -31.26225 | C33: =C18-C27-C29 -> -42.5245 | D33: =D18-D27-D29 -> -53.049 | E33: =E18-E27-E29 -> -52.83575 | F33: =F18-F27-F29 -> -51.88475 | G33: =G18-G27-G29 -> -52.93375 | H33: =H18-H27-H29 -> -43.245 | I33: =I18-I27-I29 -> -22.8185 | ... Y33: =Y18-Y27-Y29 -> 1438.6325
A34: Gross margin % | B34: =IF(B18>0,B33/B18,0) -> -1.5438148 | C34: =IF(C18>0,C33/C18,0) -> -1.0499877 | D34: =IF(D18>0,D33/D18,0) -> -0.65492593 | E34: =IF(E18>0,E33/E18,0) -> -0.37273898 | F34: =IF(F18>0,F33/F18,0) -> -0.23292817 | G34: =IF(G18>0,G33/G18,0) -> -0.17426749 | H34: =IF(H18>0,H33/H18,0) -> -0.10677778 | I34: =IF(I18>0,I33/I18,0) -> -0.043339981 | ... Y34: =IF(Y18>0,Y33/Y18,0) -> 0.28167058
A35: NET PROFIT / LOSS | B35: =B18-B30 -> -66.26225 | C35: =C18-C30 -> -77.5245 | D35: =D18-D30 -> -88.049 | E35: =E18-E30 -> -102.83575 | F35: =F18-F30 -> -101.88475 | G35: =G18-G30 -> -102.93375 | H35: =H18-H30 -> -113.245 | I35: =I18-I30 -> -92.8185 | ... Y35: =Y18-Y30 -> 1308.6325
A36: Cumulative net profit | B36: =B35 -> -66.26225 | C36: =B36+C35 -> -143.78675 | D36: =C36+D35 -> -231.83575 | E36: =D36+E35 -> -334.6715 | F36: =E36+F35 -> -436.55625 | G36: =F36+G35 -> -539.49 | H36: =G36+H35 -> -652.735 | I36: =H36+I35 -> -745.5535 | J36: =I36+J35 -> -807.20775 | ... Y36: =X36+Y35 -> 6956.106

Sheet Yearly Summary
A1: DecisionMesh — Annual P&L Summary
A3: Metric | B3: Year 1 | C3: Year 2 | D3: Y1 → Y2 Growth | E3: Notes
A4: ── SUBSCRIBERS (end of year) ──
A5: Hobby (free) | B5: ='Monthly P&L'!M7 -> 19 | C5: ='Monthly P&L'!Y7 -> 54 | D5: =IF(AND(B5<>0,C5<>0),(C5-B5)/ABS(B5),0) -> 1.8421053 | E5: Capped at 200
A6: Builder ($19/mo) | B6: ='Monthly P&L'!M8 -> 57 | C6: ='Monthly P&L'!Y8 -> 215 | D6: =IF(AND(B6<>0,C6<>0),(C6-B6)/ABS(B6),0) -> 2.7719298 | E6: ← Watch this number
A7: Pro ($49/mo) | B7: ='Monthly P&L'!M9 -> 0 | C7: ='Monthly P&L'!Y9 -> 15 | D7: =IF(AND(B7<>0,C7<>0),(C7-B7)/ABS(B7),0) -> 0
A8: Team ($149/mo) | B8: ='Monthly P&L'!M10 -> 0 | C8: ='Monthly P&L'!Y10 -> 0 | D8: =IF(AND(B8<>0,C8<>0),(C8-B8)/ABS(B8),0) -> 0
A9: Total paid subscribers | B9: ='Monthly P&L'!M11 -> 57 | C9: ='Monthly P&L'!Y11 -> 230 | D9: =IF(AND(B9<>0,C9<>0),(C9-B9)/ABS(B9),0) -> 3.0350877
A11: ── ANNUAL REVENUE ──
A12: Builder revenue | B12: =SUM('Monthly P&L'!B14:M14) -> 5016 | C12: =SUM('Monthly P&L'!N14:Y14) -> 30324 | D12: =IF(AND(B12<>0,C12<>0),(C12-B12)/ABS(B12),0) -> 5.0454545
A13: Pro revenue | B13: =SUM('Monthly P&L'!B15:M15) -> 0 | C13: =SUM('Monthly P&L'!N15:Y15) -> 4116 | D13: =IF(AND(B13<>0,C13<>0),(C13-B13)/ABS(B13),0) -> 0
A14: Team revenue | B14: =SUM('Monthly P&L'!B16:M16) -> 0 | C14: =SUM('Monthly P&L'!N16:Y16) -> 0 | D14: =IF(AND(B14<>0,C14<>0),(C14-B14)/ABS(B14),0) -> 0
A15: Credit pack sales | B15: =SUM('Monthly P&L'!B17:M17) -> 330 | C15: =SUM('Monthly P&L'!N17:Y17) -> 2100 | D15: =IF(AND(B15<>0,C15<>0),(C15-B15)/ABS(B15),0) -> 5.3636364 | E15: 5% of paid users × $25 avg
A16: TOTAL ANNUAL REVENUE | B16: =SUM('Monthly P&L'!B18:M18) -> 5346 | C16: =SUM('Monthly P&L'!N18:Y18) -> 36540 | D16: =IF(AND(B16<>0,C16<>0),(C16-B16)/ABS(B16),0) -> 5.8350168
A18: ── ANNUAL COSTS ──
A19: LLM costs (all tiers) | B19: =SUM('Monthly P&L'!B27:M27) -> 5199 | C19: =SUM('Monthly P&L'!N27:Y27) -> 25878 | D19: =IF(AND(B19<>0,C19<>0),(C19-B19)/ABS(B19),0) -> 3.9774957 | E19: ~$0.004/credit blended
A20: Infrastructure | B20: =SUM('Monthly P&L'!B28:M28) -> 675 | C20: =SUM('Monthly P&L'!N28:Y28) -> 1380 | D20: =IF(AND(B20<>0,C20<>0),(C20-B20)/ABS(B20),0) -> 1.0444444 | E20: Fly.io stack
A21: Stripe fees | B21: =SUM('Monthly P&L'!B29:M29) -> 234.234 | C21: =SUM('Monthly P&L'!N29:Y29) -> 1563.66 | D21: =IF(AND(B21<>0,C21<>0),(C21-B21)/ABS(B21),0) -> 5.6756321 | E21: 2.9% + $0.30/tx
A22: TOTAL ANNUAL COSTS | B22: =B18+B19+B20 -> 5874 | C22: =C18+C19+C20 -> 27258 | D22: =IF(AND(B22<>0,C22<>0),(C22-B22)/ABS(B22),0) -> 3.6404494
A24: ── PROFITABILITY ──
A25: Gross profit | B25: =SUM('Monthly P&L'!B33:M33) -> -87.234 | C25: =SUM('Monthly P&L'!N33:Y33) -> 9098.34 | D25: =IF(AND(B25<>0,C25<>0),(C25-B25)/ABS(B25),0) -> 105.29809 | E25: After LLM + Stripe only
A26: Gross margin % | B26: =IF(B13>0,B22/B13,0) -> 0 | C26: =IF(C13>0,C22/C13,0) -> 6.622449 | D26: =IF(AND(B26<>0,C26<>0),(C26-B26)/ABS(B26),0) -> 0 | E26: Target: >50%
A27: NET ANNUAL PROFIT / LOSS | B27: =SUM('Monthly P&L'!B35:M35) -> -762.234 | C27: =SUM('Monthly P&L'!N35:Y35) -> 7718.34 | D27: =IF(AND(B27<>0,C27<>0),(C27-B27)/ABS(B27),0) -> 11.125946 | E27: After all costs
A28: Month of break-even | B28: =IFERROR(MATCH(TRUE(),'Monthly P&L'!B36:Y36>=0,0),"N/A") -> 16 | E28: ← First month cumulative net > 0

Sheet Unit Economics
A1: DecisionMesh — Unit Economics & Optimum User Mix
A3: PER-SUBSCRIBER ECONOMICS (monthly)
A4: Tier | B4: Price/mo | C4: LLM cost/mo | D4: Stripe fee | E4: Net/mo | F4: Gross margin | G4: LTV (18mo) | H4: LLM ÷ Revenue
A5: Hobby (free) | B5: =Assumptions!B6 -> 0 | C5: =Assumptions!C6*Assumptions!B17 -> 2 | D5: =0 -> 0 | E5: =B5-C5-D5 -> -2
A6: Builder $19 | B6: =Assumptions!B7 -> 19 | C6: =Assumptions!C7*Assumptions!B17 -> 8 | D6: =B6*Assumptions!B46+Assumptions!B47 -> 0.851 | E6: =B6-C6-D6 -> 10.149 | F6: =IF(B6>0,(B6-C6)/B6,0) -> 0.57894737 | G6: =MAX(0, E6*18*(1-0.05)) -> 173.5479 | H6: =IF(B6>0,C6/B6,0) -> 0.42105263
A7: Pro $49 | B7: =Assumptions!B8 -> 49 | C7: =Assumptions!C8*Assumptions!B17 -> 24 | D7: =B7*Assumptions!B46+Assumptions!B47 -> 1.721 | E7: =B7-C7-D7 -> 23.279 | F7: =IF(B7>0,(B7-C7)/B7,0) -> 0.51020408 | G7: =MAX(0, E7*18*(1-0.03)) -> 406.45134 | H7: =IF(B7>0,C7/B7,0) -> 0.48979592
A8: Team $149 | B8: =Assumptions!B9 -> 149 | C8: =Assumptions!C9*Assumptions!B17 -> 80 | D8: =B8*Assumptions!B46+Assumptions!B47 -> 4.621 | E8: =B8-C8-D8 -> 64.379 | F8: =IF(B8>0,(B8-C8)/B8,0) -> 0.46308725 | G8: =MAX(0, E8*18*(1-0.02)) -> 1135.6456 | H8: =IF(B8>0,C8/B8,0) -> 0.53691275
A11: OPTIMUM USER MIX — monthly net profit by subscriber count
A12: Hobby | B12: Builder | C12: Pro | D12: Team | E12: Revenue/mo | F12: LLM cost | G12: Net/mo | H12: Break-even?
A13: 0 | B13: 3 | C13: 0 | D13: 0 | E13: =B13*Assumptions!B7+C13*Assumptions!B8+D13*Assumptions!B9 -> 57 | F13: =A13*Assumptions!C6*Assumptions!B17+B13*Assumptions!C7*Assumptions!B17+C13*Assumptions!C8*Assumptions!B17+D13*Assumptions!C9*Assumptions!B17 -> 24 | G13: =E13-F13-35-E13*Assumptions!B46-(B13+C13+D13)*Assumptions!B47 -> -4.553 | H13: =IF(G13>0,"✓ Profitable","✗ Loss") -> ✗ Loss
A14: 0 | B14: 5 | C14: 0 | D14: 0 | E14: =B14*Assumptions!B7+C14*Assumptions!B8+D14*Assumptions!B9 -> 95 | F14: =A14*Assumptions!C6*Assumptions!B17+B14*Assumptions!C7*Assumptions!B17+C14*Assumptions!C8*Assumptions!B17+D14*Assumptions!C9*Assumptions!B17 -> 40 | G14: =E14-F14-35-E14*Assumptions!B46-(B14+C14+D14)*Assumptions!B47 -> 15.745 | H14: =IF(G14>0,"✓ Profitable","✗ Loss") -> ✓ Profitable
A15: 0 | B15: 10 | C15: 0 | D15: 0 | E15: =B15*Assumptions!B7+C15*Assumptions!B8+D15*Assumptions!B9 -> 190 | F15: =A15*Assumptions!C6*Assumptions!B17+B15*Assumptions!C7*Assumptions!B17+C15*Assumptions!C8*Assumptions!B17+D15*Assumptions!C9*Assumptions!B17 -> 80 | G15: =E15-F15-35-E15*Assumptions!B46-(B15+C15+D15)*Assumptions!B47 -> 66.49 | H15: =IF(G15>0,"✓ Profitable","✗ Loss") -> ✓ Profitable
A16: 10 | B16: 5 | C16: 1 | D16: 0 | E16: =B16*Assumptions!B7+C16*Assumptions!B8+D16*Assumptions!B9 -> 144 | F16: =A16*Assumptions!C6*Assumptions!B17+B16*Assumptions!C7*Assumptions!B17+C16*Assumptions!C8*Assumptions!B17+D16*Assumptions!C9*Assumptions!B17 -> 84 | G16: =E16-F16-35-E16*Assumptions!B46-(B16+C16+D16)*Assumptions!B47 -> 19.024 | H16: =IF(G16>0,"✓ Profitable","✗ Loss") -> ✓ Profitable
A17: 10 | B17: 10 | C17: 3 | D17: 1 | E17: =B17*Assumptions!B7+C17*Assumptions!B8+D17*Assumptions!B9 -> 486 | F17: =A17*Assumptions!C6*Assumptions!B17+B17*Assumptions!C7*Assumptions!B17+C17*Assumptions!C8*Assumptions!B17+D17*Assumptions!C9*Assumptions!B17 -> 252 | G17: =E17-F17-35-E17*Assumptions!B46-(B17+C17+D17)*Assumptions!B47 -> 180.706 | H17: =IF(G17>0,"✓ Profitable","✗ Loss") -> ✓ Profitable
A18: 20 | B18: 15 | C18: 5 | D18: 2 | E18: =B18*Assumptions!B7+C18*Assumptions!B8+D18*Assumptions!B9 -> 828 | F18: =A18*Assumptions!C6*Assumptions!B17+B18*Assumptions!C7*Assumptions!B17+C18*Assumptions!C8*Assumptions!B17+D18*Assumptions!C9*Assumptions!B17 -> 440 | G18: =E18-F18-35-E18*Assumptions!B46-(B18+C18+D18)*Assumptions!B47 -> 322.388 | H18: =IF(G18>0,"✓ Profitable","✗ Loss") -> ✓ Profitable
A19: 50 | B19: 20 | C19: 8 | D19: 2 | E19: =B19*Assumptions!B7+C19*Assumptions!B8+D19*Assumptions!B9 -> 1070 | F19: =A19*Assumptions!C6*Assumptions!B17+B19*Assumptions!C7*Assumptions!B17+C19*Assumptions!C8*Assumptions!B17+D19*Assumptions!C9*Assumptions!B17 -> 612 | G19: =E19-F19-35-E19*Assumptions!B46-(B19+C19+D19)*Assumptions!B47 -> 382.97 | H19: =IF(G19>0,"✓ Profitable","✗ Loss") -> ✓ Profitable
A20: 100 | B20: 30 | C20: 12 | D20: 3 | E20: =B20*Assumptions!B7+C20*Assumptions!B8+D20*Assumptions!B9 -> 1605 | F20: =A20*Assumptions!C6*Assumptions!B17+B20*Assumptions!C7*Assumptions!B17+C20*Assumptions!C8*Assumptions!B17+D20*Assumptions!C9*Assumptions!B17 -> 968 | G20: =E20-F20-35-E20*Assumptions!B46-(B20+C20+D20)*Assumptions!B47 -> 541.955 | H20: =IF(G20>0,"✓ Profitable","✗ Loss") -> ✓ Profitable
A21: 0 | B21: 50 | C21: 20 | D21: 5 | E21: =B21*Assumptions!B7+C21*Assumptions!B8+D21*Assumptions!B9 -> 2675 | F21: =A21*Assumptions!C6*Assumptions!B17+B21*Assumptions!C7*Assumptions!B17+C21*Assumptions!C8*Assumptions!B17+D21*Assumptions!C9*Assumptions!B17 -> 1280 | G21: =E21-F21-35-E21*Assumptions!B46-(B21+C21+D21)*Assumptions!B47 -> 1259.925 | H21: =IF(G21>0,"✓ Profitable","✗ Loss") -> ✓ Profitable
A22: 0 | B22: 100 | C22: 30 | D22: 8 | E22: =B22*Assumptions!B7+C22*Assumptions!B8+D22*Assumptions!B9 -> 4562 | F22: =A22*Assumptions!C6*Assumptions!B17+B22*Assumptions!C7*Assumptions!B17+C22*Assumptions!C8*Assumptions!B17+D22*Assumptions!C9*Assumptions!B17 -> 2160 | G22: =E22-F22-35-E22*Assumptions!B46-(B22+C22+D22)*Assumptions!B47 -> 2193.302 | H22: =IF(G22>0,"✓ Profitable","✗ Loss") -> ✓ Profitable
A23: 0 | B23: 200 | C23: 50 | D23: 15 | E23: =B23*Assumptions!B7+C23*Assumptions!B8+D23*Assumptions!B9 -> 8485 | F23: =A23*Assumptions!C6*Assumptions!B17+B23*Assumptions!C7*Assumptions!B17+C23*Assumptions!C8*Assumptions!B17+D23*Assumptions!C9*Assumptions!B17 -> 4000 | G23: =E23-F23-35-E23*Assumptions!B46-(B23+C23+D23)*Assumptions!B47 -> 4124.435 | H23: =IF(G23>0,"✓ Profitable","✗ Loss") -> ✓ Profitable
A24: 0 | B24: 300 | C24: 100 | D24: 25 | E24: =B24*Assumptions!B7+C24*Assumptions!B8+D24*Assumptions!B9 -> 14325 | F24: =A24*Assumptions!C6*Assumptions!B17+B24*Assumptions!C7*Assumptions!B17+C24*Assumptions!C8*Assumptions!B17+D24*Assumptions!C9*Assumptions!B17 -> 6800 | G24: =E24-F24-35-E24*Assumptions!B46-(B24+C24+D24)*Assumptions!B47 -> 6947.075 | H24: =IF(G24>0,"✓ Profitable","✗ Loss") -> ✓ Profitable
A26: ★ OPTIMUM TARGET: 10 Builder + 3 Pro + 1 Team = ~$155/mo net profit from Month 5

Sheet Optimum Path
A1: DecisionMesh — Optimum User Mix Path to Profitability
A2: This sheet shows the exact user count targets per month needed to break even and reach $1k, $2k, $5k MRR milestones
A4: Month | B4: Hobby target | C4: Builder target | D4: Pro target | E4: Team target | F4: Target MRR | G4: Target net/mo | H4: Milestone
A5: M1 | B5: 0 | C5: 3 | D5: 0 | E5: 0 | F5: $57 | G5: $-20 | H5: First paying customers
A6: M2 | B6: 5 | C6: 5 | D6: 1 | E6: 0 | F6: $110 | G6: $+15 | H6: Cover infra costs
A7: M3 | B7: 10 | C7: 8 | D7: 2 | E7: 0 | F7: $200 | G7: $+70
A8: M4 | B8: 10 | C8: 10 | D8: 3 | E8: 1 | F8: $336 | G8: $+155 | H8: ★ BREAK-EVEN target
A9: M5 | B9: 15 | C9: 12 | D9: 4 | E9: 1 | F9: $385 | G9: $+190 | H9: Consistent profit
A10: M6 | B10: 20 | C10: 15 | D10: 5 | E10: 2 | F10: $584 | G10: $+310 | H10: $500+ MRR net
A11: M7 | B11: 25 | C11: 18 | D11: 6 | E11: 2 | F11: $641 | G11: $+355
A12: M8 | B12: 30 | C12: 20 | D12: 8 | E12: 3 | F12: $875 | G12: $+490
A13: M9 | B13: 40 | C13: 25 | D13: 10 | E13: 3 | F13: $962 | G13: $+540 | H13: $1k MRR approaching
A14: M10 | B14: 50 | C14: 30 | D14: 12 | E14: 4 | F14: $1,134 | G14: $+650 | H14: ★ $1k net MRR
A15: M11 | B15: 60 | C15: 35 | D15: 14 | E15: 5 | F15: $1,306 | G15: $+760
A16: M12 | B16: 80 | C16: 40 | D16: 16 | E16: 5 | F16: $1,385 | G16: $+820 | H16: End of Year 1
A17: M13 | B17: 80 | C17: 55 | D17: 20 | E17: 7 | F17: $1,888 | G17: $+1,150
A18: M14 | B18: 80 | C18: 65 | D18: 25 | E18: 8 | F18: $2,182 | G18: $+1,350
A19: M15 | B19: 80 | C19: 75 | D19: 30 | E19: 10 | F19: $2,615 | G19: $+1,650 | H19: ★ $2k net MRR
A20: M18 | B20: 100 | C20: 90 | D20: 40 | E20: 12 | F20: $3,291 | G20: $+2,100 | H20: $3k MRR net
A21: M21 | B21: 120 | C21: 120 | D21: 55 | E21: 18 | F21: $4,512 | G21: $+2,900
A22: M24 | B22: 150 | C22: 150 | D22: 70 | E22: 25 | F22: $5,960 | G22: $+3,850 | H22: ★ $5k MRR net — real business
A24: KEY INSIGHT: Every additional Builder customer after break-even = +$10.50 net profit/month
A25: Builder net margin per user: | B25: =Assumptions!B7-Assumptions!C7*Assumptions!B17-Assumptions!B7*Assumptions!B46-Assumptions!B47 -> 10.149

Sheet Scenarios
A1: DecisionMesh — 3-Scenario Analysis (Conservative / Base / Optimistic)
A3: Metric | B3: Conservative | C3: Base Case | D3: Optimistic | E3: What drives it
A4: YEAR 1
A6: Paid subscribers end Y1 | B6: 18 | C6: 38 | D6: 65 | E6: Conversion rate × churn
A7: Annual revenue | B7: $3,100 | C7: $5,600 | D7: $9,800 | E7: Builder MRR × 12 at avg count
A8: Annual LLM cost | B8: $1,800 | C8: $2,800 | D8: $4,200 | E8: Proportional to credit usage
A9: Annual infrastructure | B9: $540 | C9: $570 | D9: $600 | E9: Relatively fixed
A10: Annual net profit/loss | B10: ($1,600) | C10: ($1,050) | D10: $1,200 | E10: Fixed costs dominate Y1
A11: Break-even month | B11: M16 | C11: M13 | D11: M9 | E11: Earlier with higher conversion
A13: YEAR 2
A14: Paid subscribers end Y2 | B14: 55 | C14: 145 | D14: 280 | E14: Compounding from Y1 base
A15: Annual revenue | B15: $12,000 | C15: $37,000 | D15: $78,000 | E15: Strong MRR by M24
A16: Annual LLM cost | B16: $5,500 | C16: $10,500 | D16: $22,000 | E16: Scales with usage
A17: Annual net profit | B17: $3,200 | C17: $6,000 | D17: $22,000 | E17: Infrastructure now small % of rev
A18: Month 24 MRR | B18: $1,400 | C18: $3,800 | D18: $9,200 | E18: Run-rate annual = ×12
A19: Month 24 net margin | B19: 45% | C19: 52% | D19: 61% | E19: Improves as fixed costs diluted
A25: SCENARIO DRIVER ASSUMPTIONS
A26: Monthly signup growth | B26: 60% of base | C26: 100% of base | D26: 160% of base | E26: HN, PH, content reach
A27: Conversion rate adj. | B27: −30% | C27: As modelled | D27: +40% | E27: Onboarding quality
A28: Churn multiplier | B28: ×1.4 | C28: ×1.0 | D28: ×0.7 | E28: Product stickiness
A29: Credit pack attach | B29: 3%/mo | C29: 5%/mo | D29: 8%/mo | E29: Upsell effectiveness
